canopen/__init__.py
canopen/_version.py
canopen/emcy.py
canopen/lss.py
canopen/network.py
canopen/nmt.py
canopen/py.typed
canopen/sync.py
canopen/timestamp.py
canopen/utils.py
canopen/variable.py
canopen/node/__init__.py
canopen/node/base.py
canopen/node/local.py
canopen/node/remote.py
canopen/objectdictionary/__init__.py
canopen/objectdictionary/datatypes.py
canopen/objectdictionary/eds.py
canopen/objectdictionary/epf.py
canopen/pdo/__init__.py
canopen/pdo/base.py
canopen/profiles/__init__.py
canopen/profiles/p402.py
canopen/profiles/tools/test_p402_states.py
canopen/sdo/__init__.py
canopen/sdo/base.py
canopen/sdo/client.py
canopen/sdo/constants.py
canopen/sdo/exceptions.py
canopen/sdo/server.py
canopen-2.3.0.dist-info/LICENSE.txt
canopen-2.3.0.dist-info/METADATA
canopen-2.3.0.dist-info/WHEEL
canopen-2.3.0.dist-info/top_level.txt
canopen-2.3.0.dist-info/RECORD
