Metadata-Version: 2.1
Name: canopen
Version: 2.3.0
Summary: CANopen stack implementation
Author-email: Christian Sandberg <christiansandberg@me.com>, André Colomb <src@andre.colomb.de>, André Filipe Silva <afsilva.work@gmail.com>
License: MIT License
Project-URL: documentation, https://canopen.readthedocs.io/en/stable/
Project-URL: repository, https://github.com/christiansandberg/canopen
Classifier: Development Status :: 5 - Production/Stable
Classifier: License :: OSI Approved :: MIT License
Classifier: Operating System :: OS Independent
Classifier: Programming Language :: Python :: 3 :: Only
Classifier: Intended Audience :: Developers
Classifier: Topic :: Scientific/Engineering
Requires-Python: >=3.8
License-File: LICENSE.txt
Requires-Dist: python-can>=3.0.0
